<?xml version="1.0" encoding="utf-8" ?>
<dwsync>
<file name="PySCeS.epub" server="web.sourceforge.net/htdocs/" local="131031240910000000" remote="131031240910000000" Dst="1" />
<file name="userguide.pdf" server="web.sourceforge.net/htdocs/" local="131031240940000000" remote="131031240940000000" Dst="1" />
<file name="bg_olivier_msc_thesis.pdf" server="web.sourceforge.net/htdocs/" local="130839412970000000" remote="130839412970000000" Dst="-1" />
<file name="bg_olivier_phd_thesis.pdf" server="web.sourceforge.net/htdocs/" local="130839413050000000" remote="130839413050000000" Dst="-1" />
<file name="oli05.txt" server="web.sourceforge.net/htdocs/" local="130839413060000000" remote="130839413060000000" Dst="-1" />
<file name="olirohhof02.txt" server="web.sourceforge.net/htdocs/" local="130839413070000000" remote="130839413070000000" Dst="-1" />
<file name="olirohhof05.txt" server="web.sourceforge.net/htdocs/" local="130839413090000000" remote="130839413090000000" Dst="-1" />
<file name="PySCeS-InputFile.pdf" server="web.sourceforge.net/htdocs/" local="130839413100000000" remote="130839413100000000" Dst="-1" />
<file name="PySCeS-QuickReference.pdf" server="web.sourceforge.net/htdocs/" local="130839413120000000" remote="130839413120000000" Dst="-1" />
<file name="pysces_reference_manual.pdf" server="web.sourceforge.net/htdocs/" local="130839413150000000" remote="130839413150000000" Dst="-1" />
</dwsync>